{
  "mode": "dependencycv",
  "simple": {
    "letters": "a,b,c,d,dz,e,f,g,h,i,j,k,l,m,,n,o,p,r,s,t,u,v,w,x,y,z",
    "patterns": "4,5",
    "prohibitions": "^hl,^hr,hll,hdzm,hlg,w$,y$"
  },
  "simplecv": {
    "consonants": "b,c,d,dz,f,g,h,j,k,l,m,n,p,r,s,t,v,w,x,z",
    "vowels": "a,e,i,o,u,y",
    "patterns": "CVCCV,CVC,CVVC",
    "prohibitions": "^hl,^hr,hll,hdzm,hlg,w$,y$"
  },
  "dependencycv": {
    "consonants": "b,c,d,dz,f,g,h,j,k,l,m,n,p,r,s,t,v,w,x,z",
    "vowels": "a,e,i,o,u,y",
    "patterns": "CVCCV,CVC,CVVC",
    "prohibitions": "^hl,^hr,hll,hdzm,hlg,w$,y$",
    "transitions": [
      {
        "letter": "a",
        "nextLetters": "a,b,c,d,dz,f,g,h,i,j,k,l,m,n,p,r,s,t,u,v,w,x,z"
      },
      {
        "letter": "b",
        "nextLetters": "b,c,d,dz,e,g,i,l,o,r,s,u,x,y,z"
      },
      {
        "letter": "c",
        "nextLetters": "a,b,c,d,e,i,k,l,m,n,o,p,r,t,u,v,w,y,z"
      },
      {
        "letter": "d",
        "nextLetters": "a,b,d,e,i,l,m,n,o,r,s,u,v,w,y"
      },
      {
        "letter": "dz",
        "nextLetters": "a,d,e,i,l,m,n,o,r,u,v,w,y"
      },
      {
        "letter": "e",
        "nextLetters": "b,c,d,dz,e,f,g,h,i,j,k,l,m,n,o,p,r,s,t,u,v,w,x,z"
      },
      {
        "letter": "f",
        "nextLetters": "a,c,dz,e,f,i,l,o,r,s,t,u,x,y,z"
      },
      {
        "letter": "g",
        "nextLetters": "a,b,c,d,e,g,i,l,m,n,o,r,s,u,v,x,y"
      },
      {
        "letter": "h",
        "nextLetters": "a,dz,e,i,l,o,r,u,y"
      },
      {
        "letter": "i",
        "nextLetters": "b,c,d,dz,e,f,g,h,k,l,m,n,p,r,s,t,v,w,x,z"
      },
      {
        "letter": "j",
        "nextLetters": "a,e,m,o,u"
      },
      {
        "letter": "k",
        "nextLetters": "a,c,dz,e,f,i,k,l,m,n,o,p,r,s,t,u,v,x,y,z"
      },
      {
        "letter": "l",
        "nextLetters": "a,b,c,d,dz,e,f,g,h,i,k,l,m,n,o,p,s,t,u,v,x,y,z"
      },
      {
        "letter": "m",
        "nextLetters": "a,b,c,e,f,i,m,o,p,s,u,v,w,x,y"
      },
      {
        "letter": "n",
        "nextLetters": "a,c,d,e,g,i,k,n,o,s,t,u,x,y,z"
      },
      {
        "letter": "o",
        "nextLetters": "b,c,d,dz,f,g,h,i,j,k,l,m,n,p,r,s,t,u,v,w,x,z"
      },
      {
        "letter": "p",
        "nextLetters": "a,c,dz,e,i,l,o,p,r,t,u,x,y,z"
      },
      {
        "letter": "r",
        "nextLetters": "a,b,c,,d,e,f,g,i,k,m,n,o,p,s,t,u,v,w,x,y,z"
      },
      {
        "letter": "s",
        "nextLetters": "a,d,e,g,i,l,m,n,o,r,s,u,v,w,y"
      },
      {
        "letter": "t",
        "nextLetters": "a,c,e,i,l,m,n,o,p,r,t,u,v,w,x,y,z"
      },
      {
        "letter": "u",
        "nextLetters": "b,c,d,dz,e,f,g,h,j,k,l,m,n,o,p,r,s,t,u,v,w,x,z"
      },
      {
        "letter": "v",
        "nextLetters": "a,c,d,e,i,l,o,r,s,t,u,v,x,y,z"
      },
      {
        "letter": "w",
        "nextLetters": "a,c,e,i,o,r,x"
      },
      {
        "letter": "x",
        "nextLetters": "a,d,e,g,i,k,l,m,n,o,p,r,t,u,v,w,x,y,z"
      },
      {
        "letter": "y",
        "nextLetters": "a,b,c,d,dz,f,g,h,j,k,l,m,n,p,r,s,t,v,w,x,z"
      },
      {
        "letter": "z",
        "nextLetters": "a,e,i,k,l,m,n,o,p,r,t,u,v,w,y,z"
      }
    ]
  }
}
